alexpackagetest/__init__.py
alexpackagetest/alextestmodule.py
alexpackagetest-0.1.5.dist-info/entry_points.txt
alexpackagetest-0.1.5.dist-info/WHEEL
alexpackagetest-0.1.5.dist-info/METADATA
alexpackagetest-0.1.5.dist-info/RECORD
